tbsoc/__init__.py
tbsoc/__main__.py
tbsoc/version.py
tbsoc/entrypoints/addsoc.py
tbsoc/entrypoints/argcheck.py
tbsoc/entrypoints/fitsoc.py
tbsoc/entrypoints/loadall.py
tbsoc/entrypoints/main.py
tbsoc/entrypoints/plotsoc.py
tbsoc/entrypoints/precalc.py
tbsoc/lib/cal_tools.py
tbsoc/lib/const.py
tbsoc/lib/jax_core.py
tbsoc/lib/json_loader.py
tbsoc/lib/lm_expand.py
tbsoc/lib/plot_tools.py
tbsoc/lib/printmat.py
tbsoc/lib/read_in.py
tbsoc/lib/soc_mat.py
tbsoc/lib/write_hr.py
tbsoc/server/__init__.py
tbsoc/server/api.py
tbsoc/server/data_manager.py
tbsoc/server/main.py
tbsoc/server/schemas.py
tbsoc/server/state.py
tbsoc-3.1.0.dist-info/licenses/LICENSE
tbsoc-3.1.0.dist-info/METADATA
tbsoc-3.1.0.dist-info/WHEEL
tbsoc-3.1.0.dist-info/entry_points.txt
tbsoc-3.1.0.dist-info/top_level.txt
tbsoc-3.1.0.dist-info/RECORD
