Metadata-Version: 2.4
Name: tbsoc
Version: 3.1.0
Summary: A computational method to estimate spin-orbital interaction strength in solid state systems
Author-email: "Q. Gu" <guqq@ustc.edu.cn>
Requires-Python: >=3.9
License-File: LICENSE
Requires-Dist: numpy
Requires-Dist: scipy
Requires-Dist: matplotlib
Requires-Dist: pyyaml
Requires-Dist: jax>=0.4.0
Requires-Dist: jaxlib>=0.4.0
Requires-Dist: fastapi>=0.124.4
Requires-Dist: uvicorn>=0.38.0
Requires-Dist: python-multipart>=0.0.20
Requires-Dist: pywebview>=6.1
Requires-Dist: httpx>=0.28.1
Requires-Dist: plotly>=6.5.0
Dynamic: license-file
